kavacham/Readme.md
kavacham/__init__.py
kavacham/model.py
kavacham/predictor.py
kavacham/utils.py
kavacham-0.1.0.dist-info/LICENSE
kavacham-0.1.0.dist-info/METADATA
kavacham-0.1.0.dist-info/WHEEL
kavacham-0.1.0.dist-info/RECORD
