Metadata-Version: 2.3
Name: kavacham
Version: 0.1.0
Summary: Abusive Content Detection
License: MIT
Author: Luxshan2000
Author-email: Luxshanlux2000@gmail.com
Requires-Python: >=3.10,<4.0
Classifier: License :: OSI Approved :: MIT License
Classifier: Programming Language :: Python :: 3
Classifier: Programming Language :: Python :: 3.10
Classifier: Programming Language :: Python :: 3.11
Classifier: Programming Language :: Python :: 3.12
Classifier: Programming Language :: Python :: 3.13
Requires-Dist: gdown (>=5.0.0,<6.0.0)
Requires-Dist: torch (>=2.2.0,<3.0.0)
Requires-Dist: transformers (>=4.44.2,<5.0.0)
